README.rst
setup.cfg
setup.py
bin/subhd.py
pyTongwen/__init__.py
pyTongwen/conv.py
pyTongwen/phrase.py
pyTongwen/word.py
subhd.py.egg-info/PKG-INFO
subhd.py.egg-info/SOURCES.txt
subhd.py.egg-info/dependency_links.txt
subhd.py.egg-info/pbr.json
subhd.py.egg-info/requires.txt
subhd.py.egg-info/top_level.txt
subhd_py/__init__.py
subhd_py/compressor.py
subhd_py/core.py
subhd_py/sanitizer.py