Metadata-Version: 1.1
Name: subhd.py
Version: 0.1.4
Summary: subhd.com subtitle downloader
Home-page: https://github.com/pa4373/subhd.py
Author: Wei-Shao Tang (Frank Tang)
Author-email: pa4373@gmail.com
License: GPLv3
Download-URL: https://github.com/pa4373/subhd.py/tarball/0.1.4
Keywords: subtitle subtitles video movie episode tv show
Platform: UNKNOWN
